hybridq/__init__.py
hybridq/architecture/__init__.py
hybridq/architecture/plot.py
hybridq/architecture/utils.py
hybridq/architecture/google/__init__.py
hybridq/architecture/google/sycamore.py
hybridq/architecture/ibm/__init__.py
hybridq/architecture/ibm/eagle.py
hybridq/architecture/ibm/rochester.py
hybridq/architecture/rigetti/__init__.py
hybridq/architecture/rigetti/aspen_11.py
hybridq/architecture/rigetti/aspen_7.py
hybridq/base/__init__.py
hybridq/base/base.py
hybridq/base/property.py
hybridq/circuit/__init__.py
hybridq/circuit/circuit.py
hybridq/circuit/utils.py
hybridq/circuit/simulation/__init__.py
hybridq/circuit/simulation/clifford.py
hybridq/circuit/simulation/simulation.py
hybridq/circuit/simulation/simulation_mpi.py
hybridq/circuit/simulation/utils.py
hybridq/dm/__init__.py
hybridq/dm/circuit/__init__.py
hybridq/dm/circuit/circuit.py
hybridq/dm/circuit/simulation.py
hybridq/dm/gate/__init__.py
hybridq/dm/gate/gate.py
hybridq/dm/gate/property.py
hybridq/dm/gate/utils.py
hybridq/extras/__init__.py
hybridq/extras/random.py
hybridq/extras/architecture/__init__.py
hybridq/extras/architecture/plot/__init__.py
hybridq/extras/architecture/sycamore/__init__.py
hybridq/extras/architecture/sycamore/sycamore.py
hybridq/extras/gate/__init__.py
hybridq/extras/gate/gate.py
hybridq/extras/io/__init__.py
hybridq/extras/io/cirq.py
hybridq/extras/io/qasm.py
hybridq/extras/simulation/__init__.py
hybridq/extras/simulation/otoc.py
hybridq/gate/__init__.py
hybridq/gate/gate.py
hybridq/gate/measure.py
hybridq/gate/projection.py
hybridq/gate/property.py
hybridq/gate/utils.py
hybridq/noise/__init__.py
hybridq/noise/utils.py
hybridq/noise/channel/__init__.py
hybridq/noise/channel/channel.py
hybridq/noise/channel/utils.py
hybridq/utils/__init__.py
hybridq/utils/dot.py
hybridq/utils/transpose.py
hybridq/utils/utils.py
hybridq/utils/aligned/__init__.py
hybridq/utils/aligned/aligned_array.py
hybridq-0.8.2.data/data/lib/hybridq.so
hybridq-0.8.2.data/data/lib/hybridq_swap.so
hybridq-0.8.2.dist-info/LICENSE
hybridq-0.8.2.dist-info/METADATA
hybridq-0.8.2.dist-info/WHEEL
hybridq-0.8.2.dist-info/top_level.txt
hybridq-0.8.2.dist-info/RECORD
