Metadata-Version: 2.1
Name: hybridq
Version: 0.8.2
Summary: Hybrid Simulator for Quantum Circuits
Home-page: https://github.com/nasa/hybridq
Author: Salvatore Mandrà
Author-email: salvatore.mandra@nasa.gov
License: UNKNOWN
Project-URL: Bug Reports, https://github.com/nasa/hybridq/issues
Project-URL: Source, https://github.com/nasa/hybridq/
Keywords: simulator quantum circuits,quantum computing
Platform: UNKNOWN
Classifier: Development Status :: 4 - Beta
Classifier: License :: OSI Approved :: Apache Software License
Classifier: Intended Audience :: Science/Research
Classifier: Topic :: Scientific/Engineering
Classifier: Topic :: Scientific/Engineering :: Artificial Intelligence
Classifier: Topic :: Scientific/Engineering :: Mathematics
Classifier: Topic :: Scientific/Engineering :: Physics
Classifier: Programming Language :: C++
Classifier: Programming Language :: Python :: 3 :: Only
Classifier: Programming Language :: Python :: 3.7
Classifier: Programming Language :: Python :: 3.8
Classifier: Programming Language :: Python :: 3.9
Classifier: Operating System :: Unix
Classifier: Operating System :: MacOS
Requires-Python: >=3.7, <3.10
License-File: LICENSE
Requires-Dist: autoray
Requires-Dist: cirq
Requires-Dist: dask
Requires-Dist: docopt
Requires-Dist: dill
Requires-Dist: distributed
Requires-Dist: jax
Requires-Dist: jaxlib
Requires-Dist: kahypar
Requires-Dist: more-itertools
Requires-Dist: networkx
Requires-Dist: numba (~=0.54)
Requires-Dist: numexpr
Requires-Dist: numpy
Requires-Dist: opt-einsum
Requires-Dist: optuna
Requires-Dist: pytest
Requires-Dist: python-igraph
Requires-Dist: quimb
Requires-Dist: scipy
Requires-Dist: tqdm
